[
  {
    "date": "2013-12-13",
    "name": "A Nighthawk & Ditt Inre"
  },
  {
    "date": "2013-11-15",
    "name": "Holograms"
  },
  {
    "date": "2013-10-04",
    "name": "Kite"
  },
  {
    "date": "2013-09-20",
    "name": "Nordpolen"
  },
  {
    "date": "2013-05-10",
    "name": "Jens Lekman akustisk solospelning + DJ-set"
  },
  {
    "date": "2013-04-12",
    "name": "The Mary Onettes"
  },
  {
    "date": "2013-03-01",
    "name": "Niels Nielsen + Fredrik Strage (dj)"
  },
  {
    "date": "2013-02-01",
    "name": "Summer Heart + Westkust"
  }
]